README.rst
setup.py
kaiwen/__init__.py
kaiwen/bubble_sort.py
kaiwen/calculate_pi.py
kaiwen/english_format_checker.py
kaiwen/extract_chinese_characters.py
kaiwen/extract_numbers.py
kaiwen/generate_coupon.py
kaiwen/merge_dicts.py
kaiwen/multiline_input.py
kaiwen/recursion.py
kaiwen/word_filter.py
kaiwen.egg-info/PKG-INFO
kaiwen.egg-info/SOURCES.txt
kaiwen.egg-info/dependency_links.txt
kaiwen.egg-info/requires.txt
kaiwen.egg-info/top_level.txt