Metadata-Version: 1.1
Name: kaiwen
Version: 0.3
Summary: kaiwen's package, mainly for personal use
Home-page: http://github.com/kxue4/kaiwen
Author: kaiwen Xue
Author-email: yixian.xue@gmail.com
License: BSD License
Platform: all
Classifier: Environment :: MacOS X
Classifier: Intended Audience :: Developers
Classifier: License :: OSI Approved :: BSD License
Classifier: Programming Language :: Python
Classifier: Programming Language :: Python :: Implementation
Classifier: Programming Language :: Python :: 3.6
Classifier: Topic :: Software Development :: Libraries :: Python Modules
